IFJcode17_toolkit-1.4.13.data/data/share/applications/ifjcode17-ide.desktop
IFJcode17_toolkit-1.4.13.data/data/share/icons/hicolor/scalable/apps/ifjcode17-ide.svg
IFJcode17_toolkit-1.4.13.dist-info/DESCRIPTION.rst
IFJcode17_toolkit-1.4.13.dist-info/METADATA
IFJcode17_toolkit-1.4.13.dist-info/RECORD
IFJcode17_toolkit-1.4.13.dist-info/WHEEL
IFJcode17_toolkit-1.4.13.dist-info/entry_points.txt
IFJcode17_toolkit-1.4.13.dist-info/metadata.json
IFJcode17_toolkit-1.4.13.dist-info/top_level.txt
ifj2017/__init__.py
ifj2017/__init__.pyc
ifj2017/__pycache__/__init__.cpython-35.pyc
ifj2017/benchmark/__init__.py
ifj2017/benchmark/uploader.py
ifj2017/benchmark/__pycache__/__init__.cpython-35.pyc
ifj2017/benchmark/__pycache__/uploader.cpython-35.pyc
ifj2017/bin/linux/code
ifj2017/bin/linux/err
ifj2017/bin/linux/ic17int
ifj2017/bin/linux/ko.code
ifj2017/bin/linux/ok.code
ifj2017/bin/linux/out
ifj2017/bin/linux/program
ifj2017/bin/linux/program1
ifj2017/bin/linux/strings
ifj2017/bin/windows/README
ifj2017/bin/windows/cyggcc_s-seh-1.dll
ifj2017/bin/windows/cygstdc++-6.dll
ifj2017/bin/windows/cygwin1.dll
ifj2017/bin/windows/ic17int.exe
ifj2017/ide/__init__.py
ifj2017/ide/code_analyzer.py
ifj2017/ide/debugger_wrapper.py
ifj2017/ide/io_wrapper.py
ifj2017/ide/main.py
ifj2017/ide/settings.py
ifj2017/ide/__pycache__/__init__.cpython-35.pyc
ifj2017/ide/__pycache__/code_analyzer.cpython-35.pyc
ifj2017/ide/__pycache__/debugger_wrapper.cpython-35.pyc
ifj2017/ide/__pycache__/io_wrapper.cpython-35.pyc
ifj2017/ide/__pycache__/main.cpython-35.pyc
ifj2017/ide/__pycache__/settings.cpython-35.pyc
ifj2017/ide/assets/fonts/SourceCodePro-Medium.otf
ifj2017/ide/assets/icons/16x16.png
ifj2017/ide/assets/icons/24x24.png
ifj2017/ide/assets/icons/256x256.png
ifj2017/ide/assets/icons/32x32.png
ifj2017/ide/assets/icons/48x48.png
ifj2017/ide/assets/images/arrowRight.svg
ifj2017/ide/assets/images/clearIcon.svg
ifj2017/ide/assets/images/crossIcon.svg
ifj2017/ide/assets/images/debugNextBreakpointIcon.svg
ifj2017/ide/assets/images/debugNextLineIcon.svg
ifj2017/ide/assets/images/logo.svg
ifj2017/ide/assets/images/playBugIcon.svg
ifj2017/ide/assets/images/playIcon.svg
ifj2017/ide/assets/images/stopIcon.svg
ifj2017/ide/assets/styles/UIStyles.qml
ifj2017/ide/code/__init__.py
