Metadata-Version: 2.0
Name: IFJcode17-toolkit
Version: 1.4.13
Summary: Toolkit for IFJ17 language compiler (as project at FIT BUT in Brno) with interactive debugger and automatic tests.
Home-page: https://github.com/thejoeejoee/VUT-FIT-IFJ-2017-toolkit
Author: Josef Kolář, Son Hai Nguyen
Author-email: xkolar71@stud.fit.vutbr.cz, xnguye16@stud.fit.vutbr.cz
License: GNU GENERAL PUBLIC LICENSE Version 3
Keywords: ifj17 ifjcode17 language ide utils debugger editor
Platform: UNKNOWN
Classifier: Development Status :: 5 - Production/Stable
Classifier: Environment :: X11 Applications :: Qt
Classifier: License :: OSI Approved :: GNU Lesser General Public License v3 (LGPLv3)
Classifier: Programming Language :: Python
Classifier: Programming Language :: Python :: 3.5
Classifier: Programming Language :: Python :: 3.6
Classifier: Programming Language :: Python :: 3 :: Only
Classifier: Topic :: Scientific/Engineering
Classifier: Topic :: Utilities
Requires: termcolor
Requires: PyOpenGL
Requires: PyQt5
Requires-Dist: PyOpenGL
Requires-Dist: PyQt5 (==5.7.1)
